hierarchicalvs/__init__.py
hierarchicalvs/cal_ifp.py
hierarchicalvs/hierarchicalvs.py
hierarchicalvs/util_post_process.py
hierarchicalvs-1.1.dist-info/LICENSE
hierarchicalvs-1.1.dist-info/METADATA
hierarchicalvs-1.1.dist-info/WHEEL
hierarchicalvs-1.1.dist-info/entry_points.txt
hierarchicalvs-1.1.dist-info/top_level.txt
hierarchicalvs-1.1.dist-info/RECORD
