Metadata-Version: 2.1
Name: hierarchicalvs
Version: 1.1
Summary: a fully AI-driven virtual screening package
Author: shukaigu
Author-email: 3160101168@zju.edu.cn
Classifier: Programming Language :: Python :: 3
Classifier: License :: OSI Approved :: MIT License
Classifier: Operating System :: POSIX :: Linux
Requires-Python: >=3.6
License-File: LICENSE
Requires-Dist: pillow
Requires-Dist: rdkit ==2022.09.1
Requires-Dist: oddt
